odoo10_addon_contract_recurring_analytic_distribution-10.0.1.0.0-py2.7-nspkg.pth
odoo/addons/contract_recurring_analytic_distribution/README.rst
odoo/addons/contract_recurring_analytic_distribution/__init__.py
odoo/addons/contract_recurring_analytic_distribution/__manifest__.py
odoo/addons/contract_recurring_analytic_distribution/i18n/ca.po
odoo/addons/contract_recurring_analytic_distribution/i18n/de.po
odoo/addons/contract_recurring_analytic_distribution/i18n/el_GR.po
odoo/addons/contract_recurring_analytic_distribution/i18n/es.po
odoo/addons/contract_recurring_analytic_distribution/i18n/es_MX.po
odoo/addons/contract_recurring_analytic_distribution/i18n/fi.po
odoo/addons/contract_recurring_analytic_distribution/i18n/fr.po
odoo/addons/contract_recurring_analytic_distribution/i18n/gl.po
odoo/addons/contract_recurring_analytic_distribution/i18n/hr.po
odoo/addons/contract_recurring_analytic_distribution/i18n/hr_HR.po
odoo/addons/contract_recurring_analytic_distribution/i18n/hu.po
odoo/addons/contract_recurring_analytic_distribution/i18n/it.po
odoo/addons/contract_recurring_analytic_distribution/i18n/nl.po
odoo/addons/contract_recurring_analytic_distribution/i18n/pt.po
odoo/addons/contract_recurring_analytic_distribution/i18n/pt_BR.po
odoo/addons/contract_recurring_analytic_distribution/i18n/pt_PT.po
odoo/addons/contract_recurring_analytic_distribution/i18n/ro.po
odoo/addons/contract_recurring_analytic_distribution/i18n/sk_SK.po
odoo/addons/contract_recurring_analytic_distribution/i18n/sl.po
odoo/addons/contract_recurring_analytic_distribution/i18n/zh_CN.po
odoo/addons/contract_recurring_analytic_distribution/models/__init__.py
odoo/addons/contract_recurring_analytic_distribution/models/account_analytic_account.py
odoo/addons/contract_recurring_analytic_distribution/static/description/icon.png
odoo/addons/contract_recurring_analytic_distribution/tests/__init__.py
odoo10_addon_contract_recurring_analytic_distribution-10.0.1.0.0.dist-info/DESCRIPTION.rst
odoo10_addon_contract_recurring_analytic_distribution-10.0.1.0.0.dist-info/METADATA
odoo10_addon_contract_recurring_analytic_distribution-10.0.1.0.0.dist-info/RECORD
odoo10_addon_contract_recurring_analytic_distribution-10.0.1.0.0.dist-info/WHEEL
odoo10_addon_contract_recurring_analytic_distribution-10.0.1.0.0.dist-info/metadata.json
odoo10_addon_contract_recurring_analytic_distribution-10.0.1.0.0.dist-info/namespace_packages.txt
odoo10_addon_contract_recurring_analytic_distribution-10.0.1.0.0.dist-info/top_level.txt
