Metadata-Version: 2.0
Name: odoo10-addon-contract-recurring-analytic-distribution
Version: 10.0.1.0.0
Summary: Analytic plans on contracts recurring invoices
Home-page: https://github.com/OCA/contract/
Author: Tecnativa, Odoo Community Association (OCA)
Author-email: support@odoo-community.org
License: AGPL-3
Platform: UNKNOWN
Classifier: Programming Language :: Python
Classifier: Framework :: Odoo
Classifier: License :: OSI Approved :: GNU Affero General Public License v3
Requires-Python: ~=2.7
Requires-Dist: odoo (<10.1dev,>=10.0)
Requires-Dist: odoo10-addon-account-analytic-distribution
Requires-Dist: odoo10-addon-contract
